inmailer/__init__.py
inmailer/core.py
inmailer-0.1.4.dist-info/LICENSE
inmailer-0.1.4.dist-info/METADATA
inmailer-0.1.4.dist-info/WHEEL
inmailer-0.1.4.dist-info/top_level.txt
inmailer-0.1.4.dist-info/RECORD
