Metadata-Version: 2.2
Name: inmailer
Version: 0.1.4
Summary: A Python package that offers email utilities.
Home-page: https://github.com/AbdulWajid768/pymailer
Author: Abdul Wajid
Author-email: abdul45.wajid@gmail.com
Classifier: Programming Language :: Python :: 3
Classifier: License :: OSI Approved :: MIT License
Classifier: Operating System :: OS Independent
Requires-Python: >=3.6
License-File: LICENSE
Requires-Dist: lxml
Requires-Dist: cssutils
Requires-Dist: cssselect
Dynamic: author
Dynamic: author-email
Dynamic: classifier
Dynamic: description
Dynamic: description-content-type
Dynamic: home-page
Dynamic: requires-dist
Dynamic: requires-python
Dynamic: summary
